eliot/__init__.py
eliot/_action.py
eliot/_errors.py
eliot/_generators.py
eliot/_message.py
eliot/_output.py
eliot/_traceback.py
eliot/_util.py
eliot/_validation.py
eliot/_version.py
eliot/dask.py
eliot/filter.py
eliot/journald.py
eliot/json.py
eliot/logwriter.py
eliot/parse.py
eliot/prettyprint.py
eliot/serializers.py
eliot/stdlib.py
eliot/tai64n.py
eliot/testing.py
eliot/twisted.py
eliot/tests/__init__.py
eliot/tests/common.py
eliot/tests/strategies.py
eliot/tests/test_action.py
eliot/tests/test_api.py
eliot/tests/test_coroutines.py
eliot/tests/test_dask.py
eliot/tests/test_filter.py
eliot/tests/test_generators.py
eliot/tests/test_journald.py
eliot/tests/test_json.py
eliot/tests/test_logwriter.py
eliot/tests/test_message.py
eliot/tests/test_output.py
eliot/tests/test_parse.py
eliot/tests/test_prettyprint.py
eliot/tests/test_pyinstaller.py
eliot/tests/test_serializers.py
eliot/tests/test_stdlib.py
eliot/tests/test_tai64n.py
eliot/tests/test_testing.py
eliot/tests/test_traceback.py
eliot/tests/test_twisted.py
eliot/tests/test_util.py
eliot/tests/test_validation.py
eliot-1.17.5.dist-info/LICENSE
eliot-1.17.5.dist-info/METADATA
eliot-1.17.5.dist-info/WHEEL
eliot-1.17.5.dist-info/entry_points.txt
eliot-1.17.5.dist-info/top_level.txt
eliot-1.17.5.dist-info/RECORD
