Metadata-Version: 2.2
Name: eliot
Version: 1.17.5
Summary: Logging library that tells you why it happened
Home-page: https://github.com/itamarst/eliot/
Maintainer: Itamar Turner-Trauring
Maintainer-email: itamar@itamarst.org
License: Apache 2.0
Keywords: logging
Classifier: Intended Audience :: Developers
Classifier: License :: OSI Approved :: Apache Software License
Classifier: Operating System :: OS Independent
Classifier: Programming Language :: Python
Classifier: Programming Language :: Python :: 3
Classifier: Programming Language :: Python :: 3.9
Classifier: Programming Language :: Python :: 3.10
Classifier: Programming Language :: Python :: 3.11
Classifier: Programming Language :: Python :: 3.12
Classifier: Programming Language :: Python :: 3.13
Classifier: Programming Language :: Python :: Implementation :: CPython
Classifier: Programming Language :: Python :: Implementation :: PyPy
Classifier: Topic :: System :: Logging
Requires-Python: >=3.9.0
License-File: LICENSE
Requires-Dist: zope.interface
Requires-Dist: pyrsistent>=0.11.8
Requires-Dist: boltons>=19.0.1
Requires-Dist: orjson; implementation_name == "cpython"
Provides-Extra: journald
Requires-Dist: cffi>=1.1.2; extra == "journald"
Provides-Extra: test
Requires-Dist: hypothesis>=1.14.0; extra == "test"
Requires-Dist: testtools; extra == "test"
Requires-Dist: pytest; extra == "test"
Requires-Dist: pytest-xdist; extra == "test"
Provides-Extra: dev
Requires-Dist: setuptools>=40; extra == "dev"
Requires-Dist: twine>=1.12.1; extra == "dev"
Requires-Dist: coverage; extra == "dev"
Requires-Dist: sphinx; extra == "dev"
Requires-Dist: sphinx_rtd_theme; extra == "dev"
Requires-Dist: flake8; extra == "dev"
Requires-Dist: black; extra == "dev"
Dynamic: classifier
Dynamic: description
Dynamic: home-page
Dynamic: keywords
Dynamic: license
Dynamic: maintainer
Dynamic: maintainer-email
Dynamic: provides-extra
Dynamic: requires-dist
Dynamic: requires-python
Dynamic: summary
